auto_ml_c/Feature_structure.py
auto_ml_c/__init__.py
auto_ml_c/binary_classfication.py
Auto_Taste_ML-0.0.1.dist-info/LICENSE
Auto_Taste_ML-0.0.1.dist-info/METADATA
Auto_Taste_ML-0.0.1.dist-info/WHEEL
Auto_Taste_ML-0.0.1.dist-info/top_level.txt
Auto_Taste_ML-0.0.1.dist-info/RECORD
