Metadata-Version: 2.1
Name: Auto-Taste-ML
Version: 0.0.1
Summary: A small example package
Home-page: https://github.com/SynchronyML/Auto_Taste_ML
Author: Cui Zy
Author-email: 1776228595@qq.com
License: UNKNOWN
Project-URL: Bug Tracker, https://github.com/SynchronyML/Auto_Taste_ML/issues
Platform: UNKNOWN
Classifier: Programming Language :: Python :: 3
Classifier: License :: OSI Approved :: MIT License
Classifier: Operating System :: OS Independent
Requires-Python: >=3.8.10
License-File: LICENSE
Requires-Dist: numpy (>=1.11.0)
Requires-Dist: seaborn (>=0.11.2)
Requires-Dist: pandas (>=1.3.3)
Requires-Dist: matplotlib (>=3.4.2)
Requires-Dist: xgboost (>=1.4.0)
Requires-Dist: scikit-learn (>=0.24.2)
